collective.behavior.seo-2.0.1-py3.11-nspkg.pth
collective/behavior/seo/__init__.py
collective/behavior/seo/configure.zcml
collective/behavior/seo/interfaces.py
collective/behavior/seo/setuphandlers.py
collective/behavior/seo/testing.py
collective/behavior/seo/upgrades.py
collective/behavior/seo/upgrades.zcml
collective/behavior/seo/vocabularies.py
collective/behavior/seo/behaviors/__init__.py
collective/behavior/seo/behaviors/configure.zcml
collective/behavior/seo/behaviors/seo_fields.py
collective/behavior/seo/browser/__init__.py
collective/behavior/seo/browser/configure.zcml
collective/behavior/seo/browser/metafields.py
collective/behavior/seo/browser/metarobots.pt
collective/behavior/seo/browser/metarobots.py
collective/behavior/seo/browser/title.py
collective/behavior/seo/browser/overrides/.gitkeep
collective/behavior/seo/controlpanel/__init__.py
collective/behavior/seo/controlpanel/configure.zcml
collective/behavior/seo/controlpanel/controlpanel.py
collective/behavior/seo/controlpanel/permissions.zcml
collective/behavior/seo/locales/README.rst
collective/behavior/seo/locales/__init__.py
collective/behavior/seo/locales/collective.behavior.seo.pot
collective/behavior/seo/locales/update.py
collective/behavior/seo/locales/update.sh
collective/behavior/seo/locales/de/LC_MESSAGES/collective.behavior.seo.mo
collective/behavior/seo/locales/de/LC_MESSAGES/collective.behavior.seo.po
collective/behavior/seo/locales/nl/LC_MESSAGES/collective.behavior.seo.mo
collective/behavior/seo/locales/nl/LC_MESSAGES/collective.behavior.seo.po
collective/behavior/seo/profiles/default/browserlayer.xml
collective/behavior/seo/profiles/default/controlpanel.xml
collective/behavior/seo/profiles/default/metadata.xml
collective/behavior/seo/profiles/default/registry.xml
collective/behavior/seo/profiles/uninstall/browserlayer.xml
collective/behavior/seo/profiles/uninstall/controlpanel.xml
collective/behavior/seo/profiles/uninstall/registry.xml
collective/behavior/seo/tests/__init__.py
collective.behavior.seo-2.0.1.dist-info/LICENSE.GPL
collective.behavior.seo-2.0.1.dist-info/LICENSE.rst
collective.behavior.seo-2.0.1.dist-info/METADATA
collective.behavior.seo-2.0.1.dist-info/WHEEL
collective.behavior.seo-2.0.1.dist-info/entry_points.txt
collective.behavior.seo-2.0.1.dist-info/namespace_packages.txt
collective.behavior.seo-2.0.1.dist-info/top_level.txt
collective.behavior.seo-2.0.1.dist-info/RECORD
